rust_poly-0.1.5.dist-info/METADATA
rust_poly-0.1.5.dist-info/WHEEL
rust_poly/__init__.py
rust_poly/util.py
rust_poly/polynomial.py
rust_poly/rust_poly.cpython-38-x86_64-linux-gnu.so
rust_poly-0.1.5.dist-info/RECORD
