Metadata-Version: 2.1
Name: rust_poly
Version: 0.1.5
Classifier: Programming Language :: Rust
Classifier: Programming Language :: Python :: Implementation :: CPython
Classifier: Programming Language :: Python :: Implementation :: PyPy
Requires-Dist: numpy
Summary: Fast polynomial and rational evaluation library
Keywords: numeric,math,polynomial
Author: Jason Ross
Requires-Python: >=3.6
Project-URL: Source Code, https://github.com/Jason-S-Ross/rust_poly
